surveypie/__init__.py
surveypie/abul_naga_yalcin_index.py
surveypie/allison_foster.py
surveypie/apouey_index.py
surveypie/core.py
surveypie/structure/__init__.py
surveypie/structure/index_model.py
surveypie-0.0.1.dist-info/LICENSE.md
surveypie-0.0.1.dist-info/METADATA
surveypie-0.0.1.dist-info/WHEEL
surveypie-0.0.1.dist-info/RECORD
