Metadata-Version: 2.1
Name: surveypie
Version: 0.0.1
Summary: Polarization indices in Python
Home-page: https://github.com/hs3city/surveypie
License: MIT
Keywords: statistics,ordinal scale,Likert scale,polarization indices,inequality indices
Author: HackerSpace Trójmiasto
Requires-Python: >=3.10,<4.0
Classifier: Development Status :: 3 - Alpha
Classifier: Intended Audience :: Science/Research
Classifier: License :: OSI Approved :: MIT License
Classifier: Programming Language :: Python :: 3
Classifier: Programming Language :: Python :: 3.10
Classifier: Programming Language :: Python :: 3.11
Classifier: Programming Language :: Python :: 3.12
Classifier: Topic :: Scientific/Engineering
Classifier: Topic :: Sociology
Requires-Dist: numpy (>=1.26.4,<2.0.0)
Requires-Dist: pandas (>=2.2.2,<3.0.0)
Requires-Dist: pydantic (>=2.7.1,<3.0.0)
Requires-Dist: scipy (>=1.13.0,<2.0.0)
Project-URL: Repository, https://github.com/hs3city/surveypie
